[
  {
    "SET POINT HIGH HIGH": 161.83,
    "sapParentAvevaExternalId": "18059efb-1634-4836-bac5-9ec8e5cb6dbb",
    "Issued By": "Lisa",
    "SAP OBJECT TYPE": "IP-KJPT",
    "HAZARDOUS ATEX MARKING": "II 4 F",
    "PART NUMBER": "sbpqimo5b1",
    "source": "ION",
    "flocBarrierElementPrimary": "4ybjuuutnh3x",
    "CALIBRATED RANGE MAX_UOM": "oF",
    "SERIAL NUMBER": "cc091e69-a60a-41dd-84f4-f92fde895697",
    "SIGNAL TYPE": "Modbus",
    "HAZARDOUS AREA CERT NUMBER": "zg676ry4uhrs",
    "createdTime": "2023-08-20T14:24:41.427Z",
    "SUPPLY CODE": "EU",
    "state": "0",
    "id": 8235318,
    "flocFunctionalLocation": "k8sfgwzzd1",
    "WEIGHT (DRY)": 2.22,
    "MODEL NUMBER": "i2z5oae",
    "I/O TYPE": "AO",
    "System": "31: Sub mechanical Sys",
    "Discipline": "J: Jagan and magan",
    "HAZARDOUS AREA TEMP RATING (AS REQUIRED)": "T6",
    "PARENT TAG": "94v09l7626",
    "flocSystemId": 15,
    "SET POINT HIGH HIGH_UOM": "oF",
    "flocLocation": "xtr4",
    "SAP CATALOG PROFILE": "yfjdl7ku",
    "FIRE AREA": "iv5n",
    "CALIBRATED RANGE MAX": 183.99,
    "LAST MAINTENANCE DATE": "2023-08-21T23:31:02.406Z",
    "CALIBRATION DATE": "2023-08-25T11:13:39.978Z",
    "LAST INSPECTION DATE": "2023-08-16T23:50:06.815Z"
  },
  {
    "SET POINT HIGH HIGH": 156.04,
    "sapParentAvevaExternalId": "3de55868-4f5f-4755-8c77-052e6080a600",
    "Issued By": "Ole",
    "SAP OBJECT TYPE": "IP-IOFT",
    "HAZARDOUS ATEX MARKING": "II 6 HJ",
    "PART NUMBER": "qroon8xhfc",
    "source": "aveva",
    "flocBarrierElementPrimary": "d2415hxdgnzi",
    "CALIBRATED RANGE MAX_UOM": "PoC",
    "SERIAL NUMBER": "df1a169f-d025-4c5d-915d-7ee9b7b02932",
    "SIGNAL TYPE": "0-10V",
    "HAZARDOUS AREA CERT NUMBER": "drgxby1dauik",
    "createdTime": "2023-08-21T07:44:47.730Z",
    "SUPPLY CODE": "NA",
    "state": "0",
    "id": 8800192,
    "flocFunctionalLocation": "gt1uy3rcre",
    "WEIGHT (DRY)": 2.82,
    "MODEL NUMBER": "dtg5py9",
    "I/O TYPE": "AI",
    "System": "44: Some other sys",
    "Discipline": "C: Crane and material",
    "HAZARDOUS AREA TEMP RATING (AS REQUIRED)": "T6",
    "PARENT TAG": "s8mb3lawch",
    "flocSystemId": 90,
    "SET POINT HIGH HIGH_UOM": "oF",
    "flocLocation": "h9ky",
    "SAP CATALOG PROFILE": "9e6v25mn",
    "FIRE AREA": "75ca",
    "CALIBRATED RANGE MAX": 216.16,
    "LAST MAINTENANCE DATE": "2023-08-16T11:15:52.454Z",
    "CALIBRATION DATE": "2023-08-21T04:24:04.705Z",
    "LAST INSPECTION DATE": "2023-08-24T07:54:08.375Z"
  },
  {
    "SET POINT HIGH HIGH": 155.87,
    "sapParentAvevaExternalId": "dc614200-1907-40d6-babd-438c58ade759",
    "Issued By": "Ole",
    "SAP OBJECT TYPE": "IP-TIUT",
    "HAZARDOUS ATEX MARKING": "II 1 G",
    "PART NUMBER": "egkloc2f5a",
    "source": "ION",
    "flocBarrierElementPrimary": "gv0gpnnmuxkh",
    "CALIBRATED RANGE MAX_UOM": "oF",
    "SERIAL NUMBER": "472bd7c5-93e1-41d8-89a3-989c244682eb",
    "SIGNAL TYPE": "4-20mA",
    "HAZARDOUS AREA CERT NUMBER": "3up9cul0hxcg",
    "createdTime": "2023-08-21T19:30:49.039Z",
    "SUPPLY CODE": "EU",
    "state": "1",
    "id": 8661093,
    "flocFunctionalLocation": "8z1vlc3p09",
    "WEIGHT (DRY)": 2.6,
    "MODEL NUMBER": "scbgntp",
    "I/O TYPE": "DI",
    "System": "23: UTILITIES",
    "Discipline": "D: Gas and toxic substance",
    "HAZARDOUS AREA TEMP RATING (AS REQUIRED)": "T5",
    "PARENT TAG": "cp1ezlr9uv",
    "flocSystemId": 45,
    "SET POINT HIGH HIGH_UOM": "oC",
    "flocLocation": "f2dy",
    "SAP CATALOG PROFILE": "oz2ycom7",
    "FIRE AREA": "famz",
    "CALIBRATED RANGE MAX": 186.51,
    "LAST MAINTENANCE DATE": "2023-08-18T00:12:58.515Z",
    "CALIBRATION DATE": "2023-08-21T18:58:05.442Z",
    "LAST INSPECTION DATE": "2023-08-21T00:11:17.971Z"
  },
  {
    "SET POINT HIGH HIGH": 159.71,
    "sapParentAvevaExternalId": "666aa3ab-9154-4b44-bb71-2b6920a16f7e",
    "Issued By": "Lisa",
    "SAP OBJECT TYPE": "IP-TIUT",
    "HAZARDOUS ATEX MARKING": "II 6 HJ",
    "PART NUMBER": "lntyqsrnmu",
    "source": "ION",
    "flocBarrierElementPrimary": "m8iddc1tc0wn",
    "CALIBRATED RANGE MAX_UOM": "oF",
    "SERIAL NUMBER": "d7f86038-1b1c-4616-b6bc-13ef15a27c3e",
    "SIGNAL TYPE": "0-10V",
    "HAZARDOUS AREA CERT NUMBER": "lbbvwrjelg9c",
    "createdTime": "2023-08-24T19:05:56.072Z",
    "SUPPLY CODE": "EU",
    "state": "1",
    "id": 8469760,
    "flocFunctionalLocation": "cemfm2m3sa",
    "WEIGHT (DRY)": 2.48,
    "MODEL NUMBER": "gsexkwl",
    "I/O TYPE": "DI",
    "System": "11: Crane and fabrication",
    "Discipline": "J: Jagan and magan",
    "HAZARDOUS AREA TEMP RATING (AS REQUIRED)": "T6",
    "PARENT TAG": "x3g6fv6jbt",
    "flocSystemId": 93,
    "SET POINT HIGH HIGH_UOM": "oC",
    "flocLocation": "p992",
    "SAP CATALOG PROFILE": "mho9ud09",
    "FIRE AREA": "fl4e",
    "CALIBRATED RANGE MAX": 204.27,
    "LAST MAINTENANCE DATE": "2023-08-19T20:42:35.102Z",
    "CALIBRATION DATE": "2023-08-18T03:06:28.783Z",
    "LAST INSPECTION DATE": "2023-08-21T23:50:09.170Z"
  },
  {
    "SET POINT HIGH HIGH": 157.11,
    "sapParentAvevaExternalId": "48c34777-740c-4d88-abfc-ec65ed127237",
    "Issued By": "Haakon",
    "SAP OBJECT TYPE": "IP-KJPT",
    "HAZARDOUS ATEX MARKING": "II 9 GIJO",
    "PART NUMBER": "tlvt4dtrvc",
    "source": "sap",
    "flocBarrierElementPrimary": "3qo0kesn8dno",
    "CALIBRATED RANGE MAX_UOM": "oC",
    "SERIAL NUMBER": "79dcfde0-7e91-4f82-9d31-d033ccd5d159",
    "SIGNAL TYPE": "4-20mA",
    "HAZARDOUS AREA CERT NUMBER": "gaqf190jiyqg",
    "createdTime": "2023-08-20T18:59:45.484Z",
    "SUPPLY CODE": "ASIA",
    "state": "0",
    "id": 8548456,
    "flocFunctionalLocation": "xqehpmcpff",
    "WEIGHT (DRY)": 2.38,
    "MODEL NUMBER": "yynxrll",
    "I/O TYPE": "AO",
    "System": "44: Some other sys",
    "Discipline": "A: Assemply and Installation",
    "HAZARDOUS AREA TEMP RATING (AS REQUIRED)": "T4",
    "PARENT TAG": "eomcwk0fsp",
    "flocSystemId": 37,
    "SET POINT HIGH HIGH_UOM": "oC",
    "flocLocation": "2cec",
    "SAP CATALOG PROFILE": "w0720szu",
    "FIRE AREA": "uuub",
    "CALIBRATED RANGE MAX": 195.24,
    "LAST MAINTENANCE DATE": "2023-08-20T23:59:47.241Z",
    "CALIBRATION DATE": "2023-08-16T06:11:26.005Z",
    "LAST INSPECTION DATE": "2023-08-20T03:58:50.698Z"
  },
  {
    "SET POINT HIGH HIGH": 163.65,
    "sapParentAvevaExternalId": "4773a71b-a619-4c3e-9875-32960d8aafb7",
    "Issued By": "Ole",
    "SAP OBJECT TYPE": "IP-IOFT",
    "HAZARDOUS ATEX MARKING": "II 12 oiu",
    "PART NUMBER": "903zr7evx3",
    "source": "external",
    "flocBarrierElementPrimary": "lpvxomvgtr9o",
    "CALIBRATED RANGE MAX_UOM": "oF",
    "SERIAL NUMBER": "13cfb44c-2143-4f40-bf81-53ab01fcda80",
    "SIGNAL TYPE": "Modbus",
    "HAZARDOUS AREA CERT NUMBER": "8szp5croqnuz",
    "createdTime": "2023-08-19T12:15:10.383Z",
    "SUPPLY CODE": "ASIA",
    "state": "1",
    "id": 8184980,
    "flocFunctionalLocation": "nyfv8zemxl",
    "WEIGHT (DRY)": 2.51,
    "MODEL NUMBER": "54srlot",
    "I/O TYPE": "AO",
    "System": "23: UTILITIES",
    "Discipline": "F: Facility handling",
    "HAZARDOUS AREA TEMP RATING (AS REQUIRED)": "T5",
    "PARENT TAG": "44pw2u50ei",
    "flocSystemId": 100,
    "SET POINT HIGH HIGH_UOM": "oF",
    "flocLocation": "u5v6",
    "SAP CATALOG PROFILE": "6hh4w810",
    "FIRE AREA": "5u2y",
    "CALIBRATED RANGE MAX": 212.34,
    "LAST MAINTENANCE DATE": "2023-08-24T19:59:24.136Z",
    "CALIBRATION DATE": "2023-08-25T16:51:50.697Z",
    "LAST INSPECTION DATE": "2023-08-19T04:40:56.336Z"
  },
  {
    "SET POINT HIGH HIGH": 167.58,
    "sapParentAvevaExternalId": "f9febebd-6ee2-480b-a0e5-1d9ac3db4b38",
    "Issued By": "Michael",
    "SAP OBJECT TYPE": "IP-IOFT",
    "HAZARDOUS ATEX MARKING": "II 3 G",
    "PART NUMBER": "5m46p8j1ei",
    "source": "ION",
    "flocBarrierElementPrimary": "ycb37j4mescc",
    "CALIBRATED RANGE MAX_UOM": "PoC",
    "SERIAL NUMBER": "d3147414-dae5-4bdd-9808-cc49aed6ddea",
    "SIGNAL TYPE": "4-20mA",
    "HAZARDOUS AREA CERT NUMBER": "pnsyx3e19c1l",
    "createdTime": "2023-08-18T14:44:19.876Z",
    "SUPPLY CODE": "EU",
    "state": "0",
    "id": 8135327,
    "flocFunctionalLocation": "iie90xh412",
    "WEIGHT (DRY)": 2.48,
    "MODEL NUMBER": "27cg7e0",
    "I/O TYPE": "AI",
    "System": "32: Material uploading Sys",
    "Discipline": "A: Assemply and Installation",
    "HAZARDOUS AREA TEMP RATING (AS REQUIRED)": "T5",
    "PARENT TAG": "2t6pb0fvh5",
    "flocSystemId": 63,
    "SET POINT HIGH HIGH_UOM": "oC",
    "flocLocation": "engg",
    "SAP CATALOG PROFILE": "hbmuk1ia",
    "FIRE AREA": "8c88",
    "CALIBRATED RANGE MAX": 184.28,
    "LAST MAINTENANCE DATE": "2023-08-24T22:50:16.332Z",
    "CALIBRATION DATE": "2023-08-24T05:52:54.991Z",
    "LAST INSPECTION DATE": "2023-08-16T03:29:35.254Z"
  },
  {
    "SET POINT HIGH HIGH": 155.97,
    "sapParentAvevaExternalId": "abb82166-f2b2-4638-8310-21b08a5baa78",
    "Issued By": "Dilanka",
    "SAP OBJECT TYPE": "IP-KJPT",
    "HAZARDOUS ATEX MARKING": "II 9 GIJO",
    "PART NUMBER": "3i7bmxy2r6",
    "source": "sap",
    "flocBarrierElementPrimary": "l7m5hhh8cs3x",
    "CALIBRATED RANGE MAX_UOM": "oF",
    "SERIAL NUMBER": "e5a2560f-17e1-4ef6-b641-79448875c108",
    "SIGNAL TYPE": "Modbus",
    "HAZARDOUS AREA CERT NUMBER": "0ngknovq37hv",
    "createdTime": "2023-08-19T10:56:12.007Z",
    "SUPPLY CODE": "EU",
    "state": "1",
    "id": 8541246,
    "flocFunctionalLocation": "izzab6miqo",
    "WEIGHT (DRY)": 2.34,
    "MODEL NUMBER": "g5p2l1s",
    "I/O TYPE": "DI",
    "System": "11: Crane and fabrication",
    "Discipline": "J: Jagan and magan",
    "HAZARDOUS AREA TEMP RATING (AS REQUIRED)": "T4",
    "PARENT TAG": "oibh70l299",
    "flocSystemId": 52,
    "SET POINT HIGH HIGH_UOM": "oF",
    "flocLocation": "a9ye",
    "SAP CATALOG PROFILE": "nzdvdcgd",
    "FIRE AREA": "ff36",
    "CALIBRATED RANGE MAX": 185.04,
    "LAST MAINTENANCE DATE": "2023-08-22T04:38:52.884Z",
    "CALIBRATION DATE": "2023-08-16T14:23:44.639Z",
    "LAST INSPECTION DATE": "2023-08-21T14:25:47.409Z"
  },
  {
    "SET POINT HIGH HIGH": 168.11,
    "sapParentAvevaExternalId": "b14665c3-f599-42bd-87c0-e882ffccc9ec",
    "Issued By": "Lisa",
    "SAP OBJECT TYPE": "IP-TIUT",
    "HAZARDOUS ATEX MARKING": "II 12 oiu",
    "PART NUMBER": "rtlv9vinc0",
    "source": "sap",
    "flocBarrierElementPrimary": "n46546nfd3ls",
    "CALIBRATED RANGE MAX_UOM": "PoC",
    "SERIAL NUMBER": "0c92a40e-2ecf-4665-972a-1869e045c6a0",
    "SIGNAL TYPE": "0-10V",
    "HAZARDOUS AREA CERT NUMBER": "g5q4vm0pveuj",
    "createdTime": "2023-08-21T16:27:04.542Z",
    "SUPPLY CODE": "EU",
    "state": "0",
    "id": 8696114,
    "flocFunctionalLocation": "ho2kw2829n",
    "WEIGHT (DRY)": 2.04,
    "MODEL NUMBER": "96s77cv",
    "I/O TYPE": "DI",
    "System": "11: Crane and fabrication",
    "Discipline": "C: Crane and material",
    "HAZARDOUS AREA TEMP RATING (AS REQUIRED)": "T4",
    "PARENT TAG": "54mdwxm7gf",
    "flocSystemId": 28,
    "SET POINT HIGH HIGH_UOM": "oC",
    "flocLocation": "fy3z",
    "SAP CATALOG PROFILE": "g3gc0cs9",
    "FIRE AREA": "x5sm",
    "CALIBRATED RANGE MAX": 195.03,
    "LAST MAINTENANCE DATE": "2023-08-23T03:17:46.845Z",
    "CALIBRATION DATE": "2023-08-16T08:08:50.989Z",
    "LAST INSPECTION DATE": "2023-08-17T10:28:11.341Z"
  },
  {
    "SET POINT HIGH HIGH": 165.78,
    "sapParentAvevaExternalId": "08971e63-482f-4cb5-92eb-dbf6cfab6d1d",
    "Issued By": "Michael",
    "SAP OBJECT TYPE": "IP-KJPT",
    "HAZARDOUS ATEX MARKING": "II 9 GIJO",
    "PART NUMBER": "m5dgb1f0ci",
    "source": "sap",
    "flocBarrierElementPrimary": "f99bctevb85d",
    "CALIBRATED RANGE MAX_UOM": "oF",
    "SERIAL NUMBER": "0cc57fd6-2924-474f-9783-4d5a966c619a",
    "SIGNAL TYPE": "4-20mA",
    "HAZARDOUS AREA CERT NUMBER": "y1xo6042el95",
    "createdTime": "2023-08-20T00:21:01.973Z",
    "SUPPLY CODE": "EU",
    "state": "1",
    "id": 8509636,
    "flocFunctionalLocation": "hnt6pyjz32",
    "WEIGHT (DRY)": 2.52,
    "MODEL NUMBER": "gb5v2d4",
    "I/O TYPE": "AO",
    "System": "32: Material uploading Sys",
    "Discipline": "F: Facility handling",
    "HAZARDOUS AREA TEMP RATING (AS REQUIRED)": "T4",
    "PARENT TAG": "khnta9toxe",
    "flocSystemId": 13,
    "SET POINT HIGH HIGH_UOM": "iY",
    "flocLocation": "rtck",
    "SAP CATALOG PROFILE": "vy8jp8fj",
    "FIRE AREA": "dg57",
    "CALIBRATED RANGE MAX": 201.79,
    "LAST MAINTENANCE DATE": "2023-08-25T04:03:05.161Z",
    "CALIBRATION DATE": "2023-08-18T17:45:12.566Z",
    "LAST INSPECTION DATE": "2023-08-24T16:15:08.060Z"
  },
  {
    "SET POINT HIGH HIGH": 154.48,
    "sapParentAvevaExternalId": "501b9242-41cf-4d1d-addb-272a3c971db6",
    "Issued By": "Samit",
    "SAP OBJECT TYPE": "IP-TIUT",
    "HAZARDOUS ATEX MARKING": "II 9 GIJO",
    "PART NUMBER": "7rlfrn8wn3",
    "source": "sap",
    "flocBarrierElementPrimary": "vghdl365mjru",
    "CALIBRATED RANGE MAX_UOM": "PoC",
    "SERIAL NUMBER": "a241b4c2-9587-402a-bf5f-3821213019fe",
    "SIGNAL TYPE": "4-20mA",
    "HAZARDOUS AREA CERT NUMBER": "mccagqhu2kiu",
    "createdTime": "2023-08-22T17:52:23.428Z",
    "SUPPLY CODE": "EU",
    "state": "0",
    "id": 8824430,
    "flocFunctionalLocation": "ok4y5t6ssr",
    "WEIGHT (DRY)": 2.9,
    "MODEL NUMBER": "df2b3lz",
    "I/O TYPE": "AO",
    "System": "22: Sanitation Disposal system",
    "Discipline": "G: Gaseous sabstances",
    "HAZARDOUS AREA TEMP RATING (AS REQUIRED)": "T6",
    "PARENT TAG": "amfu38ka41",
    "flocSystemId": 20,
    "SET POINT HIGH HIGH_UOM": "oC",
    "flocLocation": "jnqt",
    "SAP CATALOG PROFILE": "pn9kb1ir",
    "FIRE AREA": "eagc",
    "CALIBRATED RANGE MAX": 204.03,
    "LAST MAINTENANCE DATE": "2023-08-20T18:03:31.248Z",
    "CALIBRATION DATE": "2023-08-18T10:25:55.219Z",
    "LAST INSPECTION DATE": "2023-08-25T03:14:16.637Z"
  },
  {
    "SET POINT HIGH HIGH": 166.56,
    "sapParentAvevaExternalId": "1a80ae50-779b-4ed7-8ade-bbfa8fd8cf83",
    "Issued By": "Michael",
    "SAP OBJECT TYPE": "IP-TIUT",
    "HAZARDOUS ATEX MARKING": "II 2 G",
    "PART NUMBER": "hxprekt9dm",
    "source": "aveva",
    "flocBarrierElementPrimary": "vm2g8n9lz66x",
    "CALIBRATED RANGE MAX_UOM": "oF",
    "SERIAL NUMBER": "88c55d1d-b100-4745-96b0-35da9b6d9da2",
    "SIGNAL TYPE": "4-20mA",
    "HAZARDOUS AREA CERT NUMBER": "dt4wkyora13o",
    "createdTime": "2023-08-20T06:52:55.083Z",
    "SUPPLY CODE": "NA",
    "state": "1",
    "id": 8909936,
    "flocFunctionalLocation": "u7cxrt7ezb",
    "WEIGHT (DRY)": 2.06,
    "MODEL NUMBER": "84iwzty",
    "I/O TYPE": "DI",
    "System": "31: Sub mechanical Sys",
    "Discipline": "J: Jagan and magan",
    "HAZARDOUS AREA TEMP RATING (AS REQUIRED)": "T5",
    "PARENT TAG": "hmzo9xveru",
    "flocSystemId": 39,
    "SET POINT HIGH HIGH_UOM": "oC",
    "flocLocation": "eitq",
    "SAP CATALOG PROFILE": "xn52ezcs",
    "FIRE AREA": "dxkg",
    "CALIBRATED RANGE MAX": 186.37,
    "LAST MAINTENANCE DATE": "2023-08-18T23:01:26.848Z",
    "CALIBRATION DATE": "2023-08-18T07:22:09.996Z",
    "LAST INSPECTION DATE": "2023-08-17T17:35:36.039Z"
  },
  {
    "SET POINT HIGH HIGH": 154.9,
    "sapParentAvevaExternalId": "45efd153-b322-49a6-9d86-d5d0f71c15cf",
    "Issued By": "Ole",
    "SAP OBJECT TYPE": "IP-IOFT",
    "HAZARDOUS ATEX MARKING": "II 6 HJ",
    "PART NUMBER": "pdaeht6lnc",
    "source": "sap",
    "flocBarrierElementPrimary": "jb6ydyjicw0z",
    "CALIBRATED RANGE MAX_UOM": "oC",
    "SERIAL NUMBER": "891bce34-7d2b-441d-92bc-9c2066802c82",
    "SIGNAL TYPE": "0-10V",
    "HAZARDOUS AREA CERT NUMBER": "sjhreahevplo",
    "createdTime": "2023-08-16T09:29:18.251Z",
    "SUPPLY CODE": "ASIA",
    "state": "0",
    "id": 8976283,
    "flocFunctionalLocation": "m6aq79cets",
    "WEIGHT (DRY)": 2.66,
    "MODEL NUMBER": "bfhn6t8",
    "I/O TYPE": "AI",
    "System": "32: Material uploading Sys",
    "Discipline": "G: Gaseous sabstances",
    "HAZARDOUS AREA TEMP RATING (AS REQUIRED)": "T6",
    "PARENT TAG": "1hmls392zg",
    "flocSystemId": 100,
    "SET POINT HIGH HIGH_UOM": "oL",
    "flocLocation": "w65x",
    "SAP CATALOG PROFILE": "dopowxsy",
    "FIRE AREA": "3pz2",
    "CALIBRATED RANGE MAX": 190.88,
    "LAST MAINTENANCE DATE": "2023-08-19T03:13:27.603Z",
    "CALIBRATION DATE": "2023-08-21T17:28:33.235Z",
    "LAST INSPECTION DATE": "2023-08-21T20:05:41.866Z"
  },
  {
    "SET POINT HIGH HIGH": 159.47,
    "sapParentAvevaExternalId": "e5de7777-faff-43db-a71b-0cdfdbee4e5b",
    "Issued By": "Ole",
    "SAP OBJECT TYPE": "IP-KJPT",
    "HAZARDOUS ATEX MARKING": "II 4 F",
    "PART NUMBER": "53ko1q689r",
    "source": "external",
    "flocBarrierElementPrimary": "wzh4dvhkrnic",
    "CALIBRATED RANGE MAX_UOM": "oC",
    "SERIAL NUMBER": "a0192061-b5b6-4fa3-9b5f-30d42e490942",
    "SIGNAL TYPE": "4-20mA",
    "HAZARDOUS AREA CERT NUMBER": "tnwofk31rywd",
    "createdTime": "2023-08-20T03:07:49.786Z",
    "SUPPLY CODE": "NA",
    "state": "1",
    "id": 8619849,
    "flocFunctionalLocation": "63ecezyiky",
    "WEIGHT (DRY)": 2.18,
    "MODEL NUMBER": "lmuxiu2",
    "I/O TYPE": "DO",
    "System": "77: Ventisjon Sys",
    "Discipline": "J: Jagan and magan",
    "HAZARDOUS AREA TEMP RATING (AS REQUIRED)": "T5",
    "PARENT TAG": "wbnr7pqb5n",
    "flocSystemId": 23,
    "SET POINT HIGH HIGH_UOM": "oC",
    "flocLocation": "bkfw",
    "SAP CATALOG PROFILE": "z4g4615z",
    "FIRE AREA": "krce",
    "CALIBRATED RANGE MAX": 217.71,
    "LAST MAINTENANCE DATE": "2023-08-23T14:28:52.232Z",
    "CALIBRATION DATE": "2023-08-16T09:12:48.429Z",
    "LAST INSPECTION DATE": "2023-08-16T14:51:36.334Z"
  },
  {
    "SET POINT HIGH HIGH": 165.57,
    "sapParentAvevaExternalId": "3221fc95-202a-4e0c-b873-866d83823f69",
    "Issued By": "Ole",
    "SAP OBJECT TYPE": "IP-TIUT",
    "HAZARDOUS ATEX MARKING": "II 39 OI",
    "PART NUMBER": "unb892ustp",
    "source": "ION",
    "flocBarrierElementPrimary": "2aavkx4ymxbb",
    "CALIBRATED RANGE MAX_UOM": "oC",
    "SERIAL NUMBER": "5b7880b3-a59d-4f86-9d4c-716313db430d",
    "SIGNAL TYPE": "Modbus",
    "HAZARDOUS AREA CERT NUMBER": "menis1bb193i",
    "createdTime": "2023-08-17T22:11:40.075Z",
    "SUPPLY CODE": "ASIA",
    "state": "1",
    "id": 8540450,
    "flocFunctionalLocation": "p2z4m8ibch",
    "WEIGHT (DRY)": 2.6,
    "MODEL NUMBER": "c35d7a6",
    "I/O TYPE": "DI",
    "System": "23: UTILITIES",
    "Discipline": "J: Jagan and magan",
    "HAZARDOUS AREA TEMP RATING (AS REQUIRED)": "T4",
    "PARENT TAG": "gljjrni8o5",
    "flocSystemId": 78,
    "SET POINT HIGH HIGH_UOM": "oC",
    "flocLocation": "lmwm",
    "SAP CATALOG PROFILE": "jzi8wo5q",
    "FIRE AREA": "h84e",
    "CALIBRATED RANGE MAX": 199.68,
    "LAST MAINTENANCE DATE": "2023-08-22T05:09:47.989Z",
    "CALIBRATION DATE": "2023-08-19T11:53:38.722Z",
    "LAST INSPECTION DATE": "2023-08-23T06:04:54.877Z"
  },
  {
    "SET POINT HIGH HIGH": 166.3,
    "sapParentAvevaExternalId": "836cd602-dde3-49d5-8a1b-adde39d9b63b",
    "Issued By": "Dilanka",
    "SAP OBJECT TYPE": "IP-TIUT",
    "HAZARDOUS ATEX MARKING": "II 1 G",
    "PART NUMBER": "i1grhzeh19",
    "source": "sap",
    "flocBarrierElementPrimary": "dctrbm2keicj",
    "CALIBRATED RANGE MAX_UOM": "oF",
    "SERIAL NUMBER": "881a10ca-6166-4d9b-b2a1-c81ed0e4cef4",
    "SIGNAL TYPE": "0-10V",
    "HAZARDOUS AREA CERT NUMBER": "0uxyrvq9kgci",
    "createdTime": "2023-08-16T17:36:16.638Z",
    "SUPPLY CODE": "EU",
    "state": "0",
    "id": 8293130,
    "flocFunctionalLocation": "bkfnx233ex",
    "WEIGHT (DRY)": 2.55,
    "MODEL NUMBER": "lvgxvhw",
    "I/O TYPE": "DI",
    "System": "22: Sanitation Disposal system",
    "Discipline": "B: Biomarine and sanity",
    "HAZARDOUS AREA TEMP RATING (AS REQUIRED)": "T6",
    "PARENT TAG": "ic7o0q18r3",
    "flocSystemId": 72,
    "SET POINT HIGH HIGH_UOM": "oF",
    "flocLocation": "1i8p",
    "SAP CATALOG PROFILE": "3obgk403",
    "FIRE AREA": "8e98",
    "CALIBRATED RANGE MAX": 196.46,
    "LAST MAINTENANCE DATE": "2023-08-21T18:12:53.655Z",
    "CALIBRATION DATE": "2023-08-20T21:08:11.024Z",
    "LAST INSPECTION DATE": "2023-08-21T15:05:17.401Z"
  },
  {
    "SET POINT HIGH HIGH": 162.77,
    "sapParentAvevaExternalId": "88b79514-5af5-4fb1-a8a1-13e32f49411c",
    "Issued By": "Michael",
    "SAP OBJECT TYPE": "IP-KJPT",
    "HAZARDOUS ATEX MARKING": "II 6 HJ",
    "PART NUMBER": "e2bk5acqah",
    "source": "ION",
    "flocBarrierElementPrimary": "yj4vfptj4nlc",
    "CALIBRATED RANGE MAX_UOM": "oF",
    "SERIAL NUMBER": "0dd4b206-ce1d-4769-bf02-7693f7dfca88",
    "SIGNAL TYPE": "Modbus",
    "HAZARDOUS AREA CERT NUMBER": "dj2jdr05bk29",
    "createdTime": "2023-08-22T20:38:27.549Z",
    "SUPPLY CODE": "NA",
    "state": "0",
    "id": 8515060,
    "flocFunctionalLocation": "dk280140md",
    "WEIGHT (DRY)": 2.93,
    "MODEL NUMBER": "7rcklf2",
    "I/O TYPE": "AI",
    "System": "23: UTILITIES",
    "Discipline": "E: Electrical",
    "HAZARDOUS AREA TEMP RATING (AS REQUIRED)": "T4",
    "PARENT TAG": "gaiacsv42f",
    "flocSystemId": 58,
    "SET POINT HIGH HIGH_UOM": "oC",
    "flocLocation": "0ruz",
    "SAP CATALOG PROFILE": "dng3lmsd",
    "FIRE AREA": "xk13",
    "CALIBRATED RANGE MAX": 186.64,
    "LAST MAINTENANCE DATE": "2023-08-17T21:32:02.717Z",
    "CALIBRATION DATE": "2023-08-21T22:39:51.682Z",
    "LAST INSPECTION DATE": "2023-08-19T23:49:38.142Z"
  },
  {
    "SET POINT HIGH HIGH": 152.09,
    "sapParentAvevaExternalId": "634bdf10-e5a4-46e4-8daa-16d36c0199d9",
    "Issued By": "Lisa",
    "SAP OBJECT TYPE": "IP-KJPT",
    "HAZARDOUS ATEX MARKING": "II 4 F",
    "PART NUMBER": "uw2taxj7bx",
    "source": "sap",
    "flocBarrierElementPrimary": "md90kurd68ni",
    "CALIBRATED RANGE MAX_UOM": "PoC",
    "SERIAL NUMBER": "51666062-2116-4a86-8fe8-6c058b4449e4",
    "SIGNAL TYPE": "4-20mA",
    "HAZARDOUS AREA CERT NUMBER": "j532zboglcdd",
    "createdTime": "2023-08-21T22:36:15.885Z",
    "SUPPLY CODE": "NA",
    "state": "0",
    "id": 8536025,
    "flocFunctionalLocation": "l7n61lhva3",
    "WEIGHT (DRY)": 2.39,
    "MODEL NUMBER": "7pgbkxn",
    "I/O TYPE": "AO",
    "System": "21: CRUDE HANDLING AND METERING",
    "Discipline": "J: Jagan and magan",
    "HAZARDOUS AREA TEMP RATING (AS REQUIRED)": "T6",
    "PARENT TAG": "3bstejlcir",
    "flocSystemId": 16,
    "SET POINT HIGH HIGH_UOM": "oC",
    "flocLocation": "sma9",
    "SAP CATALOG PROFILE": "4sbjompc",
    "FIRE AREA": "llrl",
    "CALIBRATED RANGE MAX": 202.94,
    "LAST MAINTENANCE DATE": "2023-08-19T06:55:16.303Z",
    "CALIBRATION DATE": "2023-08-22T22:04:11.156Z",
    "LAST INSPECTION DATE": "2023-08-23T14:14:41.788Z"
  },
  {
    "SET POINT HIGH HIGH": 152.08,
    "sapParentAvevaExternalId": "5370e641-6896-4d04-922c-9ff2de2424c4",
    "Issued By": "Ole",
    "SAP OBJECT TYPE": "IP-KJPT",
    "HAZARDOUS ATEX MARKING": "II 39 OI",
    "PART NUMBER": "w2a86lpcen",
    "source": "external",
    "flocBarrierElementPrimary": "ktbjirmjat8o",
    "CALIBRATED RANGE MAX_UOM": "oF",
    "SERIAL NUMBER": "b991b318-b4bf-4ca9-a2e3-dfc69220dfcb",
    "SIGNAL TYPE": "Modbus",
    "HAZARDOUS AREA CERT NUMBER": "q9v5rd3372w0",
    "createdTime": "2023-08-21T21:21:23.269Z",
    "SUPPLY CODE": "EU",
    "state": "0",
    "id": 8838797,
    "flocFunctionalLocation": "yeu1wiust0",
    "WEIGHT (DRY)": 2.94,
    "MODEL NUMBER": "sxxrxnz",
    "I/O TYPE": "AI",
    "System": "11: Crane and fabrication",
    "Discipline": "C: Crane and material",
    "HAZARDOUS AREA TEMP RATING (AS REQUIRED)": "T4",
    "PARENT TAG": "5unjcw04o4",
    "flocSystemId": 99,
    "SET POINT HIGH HIGH_UOM": "oC",
    "flocLocation": "q8uv",
    "SAP CATALOG PROFILE": "smj51ao2",
    "FIRE AREA": "tm0i",
    "CALIBRATED RANGE MAX": 190.18,
    "LAST MAINTENANCE DATE": "2023-08-16T11:20:16.487Z",
    "CALIBRATION DATE": "2023-08-16T02:27:17.249Z",
    "LAST INSPECTION DATE": "2023-08-19T16:39:50.270Z"
  },
  {
    "SET POINT HIGH HIGH": 154.03,
    "sapParentAvevaExternalId": "14ca56e5-adc6-4a21-980d-85edfeacfbbf",
    "Issued By": "Vaibhav",
    "SAP OBJECT TYPE": "IP-KJPT",
    "HAZARDOUS ATEX MARKING": "II 2 G",
    "PART NUMBER": "6n3lguh7u7",
    "source": "ION",
    "flocBarrierElementPrimary": "c0rj0wu6bwcf",
    "CALIBRATED RANGE MAX_UOM": "PoC",
    "SERIAL NUMBER": "c1f5a64b-95c5-4086-8be0-8429fe9ed14f",
    "SIGNAL TYPE": "4-20mA",
    "HAZARDOUS AREA CERT NUMBER": "bj6gyiai7uy9",
    "createdTime": "2023-08-20T11:04:44.202Z",
    "SUPPLY CODE": "NA",
    "state": "0",
    "id": 8532897,
    "flocFunctionalLocation": "au9ye18q5p",
    "WEIGHT (DRY)": 3,
    "MODEL NUMBER": "d2u0q02",
    "I/O TYPE": "AI",
    "System": "44: Some other sys",
    "Discipline": "E: Electrical",
    "HAZARDOUS AREA TEMP RATING (AS REQUIRED)": "T6",
    "PARENT TAG": "ipkas8u7c2",
    "flocSystemId": 85,
    "SET POINT HIGH HIGH_UOM": "oC",
    "flocLocation": "ytq0",
    "SAP CATALOG PROFILE": "zhjml22q",
    "FIRE AREA": "gcl0",
    "CALIBRATED RANGE MAX": 185.4,
    "LAST MAINTENANCE DATE": "2023-08-20T13:36:55.704Z",
    "CALIBRATION DATE": "2023-08-23T05:52:09.764Z",
    "LAST INSPECTION DATE": "2023-08-19T20:00:10.588Z"
  },
  {
    "SET POINT HIGH HIGH": 152.7,
    "sapParentAvevaExternalId": "fa0a399a-a4df-4796-86d3-c841addca58b",
    "Issued By": "Samit",
    "SAP OBJECT TYPE": "IP-IOFT",
    "HAZARDOUS ATEX MARKING": "II 4 F",
    "PART NUMBER": "up5nkp1z6s",
    "source": "aveva",
    "flocBarrierElementPrimary": "jgcrwk5qow32",
    "CALIBRATED RANGE MAX_UOM": "oF",
    "SERIAL NUMBER": "7e061725-0179-4081-91d4-8f1a73e4bc01",
    "SIGNAL TYPE": "0-10V",
    "HAZARDOUS AREA CERT NUMBER": "1uz6oecahh08",
    "createdTime": "2023-08-21T00:30:54.985Z",
    "SUPPLY CODE": "NA",
    "state": "1",
    "id": 8876798,
    "flocFunctionalLocation": "c2gy2t8j4a",
    "WEIGHT (DRY)": 2.34,
    "MODEL NUMBER": "zbme8ku",
    "I/O TYPE": "DO",
    "System": "77: Ventisjon Sys",
    "Discipline": "A: Assemply and Installation",
    "HAZARDOUS AREA TEMP RATING (AS REQUIRED)": "T4",
    "PARENT TAG": "kzf02n4nun",
    "flocSystemId": 76,
    "SET POINT HIGH HIGH_UOM": "iY",
    "flocLocation": "fkck",
    "SAP CATALOG PROFILE": "ugmo4ves",
    "FIRE AREA": "zqsp",
    "CALIBRATED RANGE MAX": 202.24,
    "LAST MAINTENANCE DATE": "2023-08-19T10:33:11.194Z",
    "CALIBRATION DATE": "2023-08-22T20:37:29.581Z",
    "LAST INSPECTION DATE": "2023-08-23T15:49:30.845Z"
  },
  {
    "SET POINT HIGH HIGH": 167.57,
    "sapParentAvevaExternalId": "74f66d98-75d1-4f18-b946-1074275c7dd8",
    "Issued By": "Samit",
    "SAP OBJECT TYPE": "IP-KJPT",
    "HAZARDOUS ATEX MARKING": "II 6 HJ",
    "PART NUMBER": "hjitvdx9sl",
    "source": "aveva",
    "flocBarrierElementPrimary": "n5wxsbf64eks",
    "CALIBRATED RANGE MAX_UOM": "oC",
    "SERIAL NUMBER": "48ad7fe3-7fc5-4f8a-8920-4b1dc2a5f2cf",
    "SIGNAL TYPE": "0-10V",
    "HAZARDOUS AREA CERT NUMBER": "irhi06pdi6yr",
    "createdTime": "2023-08-22T14:38:32.448Z",
    "SUPPLY CODE": "ASIA",
    "state": "0",
    "id": 8561843,
    "flocFunctionalLocation": "g3pdqhjtux",
    "WEIGHT (DRY)": 2.74,
    "MODEL NUMBER": "n3w49gx",
    "I/O TYPE": "AO",
    "System": "44: Some other sys",
    "Discipline": "J: Jagan and magan",
    "HAZARDOUS AREA TEMP RATING (AS REQUIRED)": "T4",
    "PARENT TAG": "aool3axdey",
    "flocSystemId": 55,
    "SET POINT HIGH HIGH_UOM": "oC",
    "flocLocation": "g4vs",
    "SAP CATALOG PROFILE": "oyxtx9bl",
    "FIRE AREA": "6m0g",
    "CALIBRATED RANGE MAX": 204.09,
    "LAST MAINTENANCE DATE": "2023-08-25T20:17:09.548Z",
    "CALIBRATION DATE": "2023-08-20T13:04:49.833Z",
    "LAST INSPECTION DATE": "2023-08-19T19:01:26.235Z"
  },
  {
    "SET POINT HIGH HIGH": 160.12,
    "sapParentAvevaExternalId": "72c0158d-2fb2-4259-8b6b-a500982dd793",
    "Issued By": "Ole",
    "SAP OBJECT TYPE": "IP-IOFT",
    "HAZARDOUS ATEX MARKING": "II 1 G",
    "PART NUMBER": "82zte0a5ny",
    "source": "external",
    "flocBarrierElementPrimary": "sc9jzavo9p7v",
    "CALIBRATED RANGE MAX_UOM": "oC",
    "SERIAL NUMBER": "ab133e0f-8098-4e51-aeb5-2f17284b47d0",
    "SIGNAL TYPE": "Modbus",
    "HAZARDOUS AREA CERT NUMBER": "w3wmxwm5xcpp",
    "createdTime": "2023-08-19T05:11:19.982Z",
    "SUPPLY CODE": "ASIA",
    "state": "0",
    "id": 8517850,
    "flocFunctionalLocation": "2tjc6uulnp",
    "WEIGHT (DRY)": 3,
    "MODEL NUMBER": "lmyccit",
    "I/O TYPE": "AI",
    "System": "22: GAS PROCESSING",
    "Discipline": "E: Electrical",
    "HAZARDOUS AREA TEMP RATING (AS REQUIRED)": "T5",
    "PARENT TAG": "17ahsclihr",
    "flocSystemId": 21,
    "SET POINT HIGH HIGH_UOM": "oL",
    "flocLocation": "amar",
    "SAP CATALOG PROFILE": "x9qd0piw",
    "FIRE AREA": "4alg",
    "CALIBRATED RANGE MAX": 217.35,
    "LAST MAINTENANCE DATE": "2023-08-16T00:55:19.382Z",
    "CALIBRATION DATE": "2023-08-22T16:15:28.825Z",
    "LAST INSPECTION DATE": "2023-08-16T12:50:57.282Z"
  },
  {
    "SET POINT HIGH HIGH": 150.22,
    "sapParentAvevaExternalId": "bb7b65af-0f5c-49d8-bbed-d6f8864b210c",
    "Issued By": "Ole",
    "SAP OBJECT TYPE": "IP-TIUT",
    "HAZARDOUS ATEX MARKING": "II 6 HJ",
    "PART NUMBER": "fem4umyznu",
    "source": "aveva",
    "flocBarrierElementPrimary": "i8zx0riwai7f",
    "CALIBRATED RANGE MAX_UOM": "oC",
    "SERIAL NUMBER": "f6b155d5-93e5-4456-a2c2-0baa79d6e4e2",
    "SIGNAL TYPE": "4-20mA",
    "HAZARDOUS AREA CERT NUMBER": "tq53d7ne528s",
    "createdTime": "2023-08-17T05:13:42.918Z",
    "SUPPLY CODE": "EU",
    "state": "1",
    "id": 8130608,
    "flocFunctionalLocation": "t1ahifbxhp",
    "WEIGHT (DRY)": 2.52,
    "MODEL NUMBER": "du35ly6",
    "I/O TYPE": "DI",
    "System": "32: Material uploading Sys",
    "Discipline": "J: Jagan and magan",
    "HAZARDOUS AREA TEMP RATING (AS REQUIRED)": "T5",
    "PARENT TAG": "p23re9ogug",
    "flocSystemId": 38,
    "SET POINT HIGH HIGH_UOM": "oL",
    "flocLocation": "vo3i",
    "SAP CATALOG PROFILE": "3cyz6kcb",
    "FIRE AREA": "xizn",
    "CALIBRATED RANGE MAX": 195.64,
    "LAST MAINTENANCE DATE": "2023-08-18T04:03:21.660Z",
    "CALIBRATION DATE": "2023-08-18T15:41:04.499Z",
    "LAST INSPECTION DATE": "2023-08-20T05:11:23.381Z"
  },
  {
    "SET POINT HIGH HIGH": 153.97,
    "sapParentAvevaExternalId": "37aaf5bf-9f46-422a-a83f-9c07fa417517",
    "Issued By": "Lisa",
    "SAP OBJECT TYPE": "IP-KJPT",
    "HAZARDOUS ATEX MARKING": "II 2 G",
    "PART NUMBER": "2oy79kzwv0",
    "source": "sap",
    "flocBarrierElementPrimary": "iovxtmq1n7qp",
    "CALIBRATED RANGE MAX_UOM": "oC",
    "SERIAL NUMBER": "06d0bd3a-7fd4-4a7a-b60d-392477879b2e",
    "SIGNAL TYPE": "4-20mA",
    "HAZARDOUS AREA CERT NUMBER": "mgdadpzgjd68",
    "createdTime": "2023-08-20T06:37:53.443Z",
    "SUPPLY CODE": "EU",
    "state": "0",
    "id": 8987547,
    "flocFunctionalLocation": "0zjskk9rvn",
    "WEIGHT (DRY)": 3,
    "MODEL NUMBER": "tu15v60",
    "I/O TYPE": "DO",
    "System": "32: Material uploading Sys",
    "Discipline": "G: Gaseous sabstances",
    "HAZARDOUS AREA TEMP RATING (AS REQUIRED)": "T5",
    "PARENT TAG": "h0gwspwoks",
    "flocSystemId": 43,
    "SET POINT HIGH HIGH_UOM": "oF",
    "flocLocation": "2830",
    "SAP CATALOG PROFILE": "pz0guym4",
    "FIRE AREA": "jmvw",
    "CALIBRATED RANGE MAX": 189.13,
    "LAST MAINTENANCE DATE": "2023-08-19T11:45:07.952Z",
    "CALIBRATION DATE": "2023-08-24T00:09:36.745Z",
    "LAST INSPECTION DATE": "2023-08-22T14:38:24.378Z"
  },
  {
    "SET POINT HIGH HIGH": 152.32,
    "sapParentAvevaExternalId": "bd2b5102-4755-4cc8-b313-c467f4d343e2",
    "Issued By": "Ole",
    "SAP OBJECT TYPE": "IP-KJPT",
    "HAZARDOUS ATEX MARKING": "II 2 G",
    "PART NUMBER": "p24obr51io",
    "source": "external",
    "flocBarrierElementPrimary": "bptjl37mm68r",
    "CALIBRATED RANGE MAX_UOM": "oC",
    "SERIAL NUMBER": "c8891ccc-5c97-4756-a909-824a3604f811",
    "SIGNAL TYPE": "0-10V",
    "HAZARDOUS AREA CERT NUMBER": "zq876k3oluvw",
    "createdTime": "2023-08-24T23:34:10.921Z",
    "SUPPLY CODE": "ASIA",
    "state": "0",
    "id": 8548878,
    "flocFunctionalLocation": "21h7iun0qz",
    "WEIGHT (DRY)": 2.69,
    "MODEL NUMBER": "lr1g319",
    "I/O TYPE": "AI",
    "System": "22: Sanitation Disposal system",
    "Discipline": "E: Electrical",
    "HAZARDOUS AREA TEMP RATING (AS REQUIRED)": "T5",
    "PARENT TAG": "kzh7sr1qth",
    "flocSystemId": 80,
    "SET POINT HIGH HIGH_UOM": "oC",
    "flocLocation": "1ro5",
    "SAP CATALOG PROFILE": "onhnwq0e",
    "FIRE AREA": "840u",
    "CALIBRATED RANGE MAX": 207.06,
    "LAST MAINTENANCE DATE": "2023-08-21T04:35:00.112Z",
    "CALIBRATION DATE": "2023-08-23T06:41:34.561Z",
    "LAST INSPECTION DATE": "2023-08-25T20:48:35.367Z"
  },
  {
    "SET POINT HIGH HIGH": 160.41,
    "sapParentAvevaExternalId": "c69268b6-5f77-4ac5-ab3f-accb641b83d6",
    "Issued By": "Haakon",
    "SAP OBJECT TYPE": "IP-IOFT",
    "HAZARDOUS ATEX MARKING": "II 9 GIJO",
    "PART NUMBER": "hbnd4hv819",
    "source": "external",
    "flocBarrierElementPrimary": "bcgqa0r0797a",
    "CALIBRATED RANGE MAX_UOM": "oF",
    "SERIAL NUMBER": "f290cb57-a31b-4970-9dd3-bb47cedef991",
    "SIGNAL TYPE": "Modbus",
    "HAZARDOUS AREA CERT NUMBER": "iykbpdvmmuae",
    "createdTime": "2023-08-22T04:59:00.305Z",
    "SUPPLY CODE": "ASIA",
    "state": "0",
    "id": 8305528,
    "flocFunctionalLocation": "1nubgjlyez",
    "WEIGHT (DRY)": 2.94,
    "MODEL NUMBER": "mmy2373",
    "I/O TYPE": "AI",
    "System": "44: Some other sys",
    "Discipline": "E: Electrical",
    "HAZARDOUS AREA TEMP RATING (AS REQUIRED)": "T6",
    "PARENT TAG": "pvtpvc4di4",
    "flocSystemId": 4,
    "SET POINT HIGH HIGH_UOM": "oC",
    "flocLocation": "z0kg",
    "SAP CATALOG PROFILE": "1kd7ritc",
    "FIRE AREA": "ciaa",
    "CALIBRATED RANGE MAX": 212.44,
    "LAST MAINTENANCE DATE": "2023-08-20T02:50:51.779Z",
    "CALIBRATION DATE": "2023-08-24T23:21:04.320Z",
    "LAST INSPECTION DATE": "2023-08-25T07:58:50.049Z"
  },
  {
    "SET POINT HIGH HIGH": 158.57,
    "sapParentAvevaExternalId": "e934683d-0eee-4e7e-b461-684e3124a28e",
    "Issued By": "Haakon",
    "SAP OBJECT TYPE": "IP-IOFT",
    "HAZARDOUS ATEX MARKING": "II 3 G",
    "PART NUMBER": "iwpizp1ge0",
    "source": "external",
    "flocBarrierElementPrimary": "h32nuz7wrzq2",
    "CALIBRATED RANGE MAX_UOM": "oC",
    "SERIAL NUMBER": "fa288d9b-04dd-4d7e-9132-a84fe43d43a6",
    "SIGNAL TYPE": "4-20mA",
    "HAZARDOUS AREA CERT NUMBER": "d290hnhlbwsl",
    "createdTime": "2023-08-16T20:01:44.152Z",
    "SUPPLY CODE": "ASIA",
    "state": "1",
    "id": 8378521,
    "flocFunctionalLocation": "rsiz70iizi",
    "WEIGHT (DRY)": 2.78,
    "MODEL NUMBER": "0kujaf0",
    "I/O TYPE": "DO",
    "System": "44: Some other sys",
    "Discipline": "C: Crane and material",
    "HAZARDOUS AREA TEMP RATING (AS REQUIRED)": "T4",
    "PARENT TAG": "geitllyljl",
    "flocSystemId": 80,
    "SET POINT HIGH HIGH_UOM": "oF",
    "flocLocation": "qard",
    "SAP CATALOG PROFILE": "f2i5lmgd",
    "FIRE AREA": "42w8",
    "CALIBRATED RANGE MAX": 199.93,
    "LAST MAINTENANCE DATE": "2023-08-19T20:08:46.928Z",
    "CALIBRATION DATE": "2023-08-22T11:12:40.148Z",
    "LAST INSPECTION DATE": "2023-08-24T21:14:22.744Z"
  },
  {
    "SET POINT HIGH HIGH": 150.9,
    "sapParentAvevaExternalId": "936f4376-1bd1-4c99-b113-cb1169a4569f",
    "Issued By": "Lisa",
    "SAP OBJECT TYPE": "IP-TIUT",
    "HAZARDOUS ATEX MARKING": "II 4 F",
    "PART NUMBER": "3687y5xa2k",
    "source": "aveva",
    "flocBarrierElementPrimary": "q4q32jm7m50i",
    "CALIBRATED RANGE MAX_UOM": "oC",
    "SERIAL NUMBER": "06272a7e-931f-4c9a-b5ea-5f93847c3c18",
    "SIGNAL TYPE": "0-10V",
    "HAZARDOUS AREA CERT NUMBER": "p6dwn14mmo16",
    "createdTime": "2023-08-20T05:33:41.793Z",
    "SUPPLY CODE": "EU",
    "state": "1",
    "id": 8447919,
    "flocFunctionalLocation": "tzrboymww7",
    "WEIGHT (DRY)": 2.52,
    "MODEL NUMBER": "fzhf1uj",
    "I/O TYPE": "DI",
    "System": "44: Some other sys",
    "Discipline": "D: Gas and toxic substance",
    "HAZARDOUS AREA TEMP RATING (AS REQUIRED)": "T4",
    "PARENT TAG": "68m8wlee0c",
    "flocSystemId": 29,
    "SET POINT HIGH HIGH_UOM": "oL",
    "flocLocation": "5vhb",
    "SAP CATALOG PROFILE": "9r8h4uh5",
    "FIRE AREA": "dfqe",
    "CALIBRATED RANGE MAX": 218.06,
    "LAST MAINTENANCE DATE": "2023-08-17T11:44:06.862Z",
    "CALIBRATION DATE": "2023-08-25T18:14:05.443Z",
    "LAST INSPECTION DATE": "2023-08-19T00:04:02.622Z"
  },
  {
    "SET POINT HIGH HIGH": 163.35,
    "sapParentAvevaExternalId": "95ac878c-f1d6-4a5e-99b0-e3b4955e1856",
    "Issued By": "Vaibhav",
    "SAP OBJECT TYPE": "IP-TIUT",
    "HAZARDOUS ATEX MARKING": "II 12 oiu",
    "PART NUMBER": "6xpp4kt535",
    "source": "ION",
    "flocBarrierElementPrimary": "i4d954hyi6t2",
    "CALIBRATED RANGE MAX_UOM": "oF",
    "SERIAL NUMBER": "5b42ceda-308f-4624-b421-388cba4aceea",
    "SIGNAL TYPE": "0-10V",
    "HAZARDOUS AREA CERT NUMBER": "ftwublvcyy2h",
    "createdTime": "2023-08-21T11:38:07.359Z",
    "SUPPLY CODE": "EU",
    "state": "1",
    "id": 8377553,
    "flocFunctionalLocation": "b49rg0veba",
    "WEIGHT (DRY)": 2.64,
    "MODEL NUMBER": "vpbnzyn",
    "I/O TYPE": "AO",
    "System": "11: Crane and fabrication",
    "Discipline": "G: Gaseous sabstances",
    "HAZARDOUS AREA TEMP RATING (AS REQUIRED)": "T4",
    "PARENT TAG": "9rqfz4xi4z",
    "flocSystemId": 80,
    "SET POINT HIGH HIGH_UOM": "iY",
    "flocLocation": "mz36",
    "SAP CATALOG PROFILE": "mh31s0v9",
    "FIRE AREA": "csbd",
    "CALIBRATED RANGE MAX": 180.94,
    "LAST MAINTENANCE DATE": "2023-08-17T18:07:03.522Z",
    "CALIBRATION DATE": "2023-08-23T16:42:56.236Z",
    "LAST INSPECTION DATE": "2023-08-21T04:47:21.763Z"
  },
  {
    "SET POINT HIGH HIGH": 166.77,
    "sapParentAvevaExternalId": "9e5e448a-fb21-4e47-86eb-853675dc2d5d",
    "Issued By": "Vaibhav",
    "SAP OBJECT TYPE": "IP-KJPT",
    "HAZARDOUS ATEX MARKING": "II 2 G",
    "PART NUMBER": "doy8jaxqj9",
    "source": "external",
    "flocBarrierElementPrimary": "i72f7817igiy",
    "CALIBRATED RANGE MAX_UOM": "PoC",
    "SERIAL NUMBER": "d7b68fba-526e-4fc6-a35a-841b40e11898",
    "SIGNAL TYPE": "4-20mA",
    "HAZARDOUS AREA CERT NUMBER": "5josmof2df12",
    "createdTime": "2023-08-17T19:12:10.967Z",
    "SUPPLY CODE": "EU",
    "state": "0",
    "id": 8801224,
    "flocFunctionalLocation": "z8spsmu6q1",
    "WEIGHT (DRY)": 2.38,
    "MODEL NUMBER": "n7ycue6",
    "I/O TYPE": "AO",
    "System": "32: Material uploading Sys",
    "Discipline": "F: Facility handling",
    "HAZARDOUS AREA TEMP RATING (AS REQUIRED)": "T5",
    "PARENT TAG": "gq97o7mo7v",
    "flocSystemId": 4,
    "SET POINT HIGH HIGH_UOM": "oF",
    "flocLocation": "on5s",
    "SAP CATALOG PROFILE": "29xkz6vs",
    "FIRE AREA": "01fd",
    "CALIBRATED RANGE MAX": 212.86,
    "LAST MAINTENANCE DATE": "2023-08-23T04:41:00.511Z",
    "CALIBRATION DATE": "2023-08-23T11:58:45.351Z",
    "LAST INSPECTION DATE": "2023-08-18T10:35:59.266Z"
  },
  {
    "SET POINT HIGH HIGH": 164.18,
    "sapParentAvevaExternalId": "e748752f-178e-46a5-853b-0336394481f8",
    "Issued By": "Lisa",
    "SAP OBJECT TYPE": "IP-KJPT",
    "HAZARDOUS ATEX MARKING": "II 39 OI",
    "PART NUMBER": "mxft0b50j6",
    "source": "external",
    "flocBarrierElementPrimary": "nxbqh4id9rrm",
    "CALIBRATED RANGE MAX_UOM": "PoC",
    "SERIAL NUMBER": "160075e4-46ba-42dd-9b4f-374877afa9b0",
    "SIGNAL TYPE": "4-20mA",
    "HAZARDOUS AREA CERT NUMBER": "4134ktggfdrk",
    "createdTime": "2023-08-18T10:01:48.835Z",
    "SUPPLY CODE": "NA",
    "state": "1",
    "id": 8004578,
    "flocFunctionalLocation": "vga47b8hoz",
    "WEIGHT (DRY)": 2.85,
    "MODEL NUMBER": "xlpwzj1",
    "I/O TYPE": "AO",
    "System": "32: Material uploading Sys",
    "Discipline": "G: Gaseous sabstances",
    "HAZARDOUS AREA TEMP RATING (AS REQUIRED)": "T4",
    "PARENT TAG": "jsk913lmkd",
    "flocSystemId": 88,
    "SET POINT HIGH HIGH_UOM": "oL",
    "flocLocation": "6c9a",
    "SAP CATALOG PROFILE": "6k820k0l",
    "FIRE AREA": "4xwc",
    "CALIBRATED RANGE MAX": 181.41,
    "LAST MAINTENANCE DATE": "2023-08-25T01:18:17.107Z",
    "CALIBRATION DATE": "2023-08-22T07:13:26.353Z",
    "LAST INSPECTION DATE": "2023-08-25T04:39:43.181Z"
  },
  {
    "SET POINT HIGH HIGH": 155.69,
    "sapParentAvevaExternalId": "11530cbc-1739-4631-b0e3-8c6613463d92",
    "Issued By": "Haakon",
    "SAP OBJECT TYPE": "IP-KJPT",
    "HAZARDOUS ATEX MARKING": "II 6 HJ",
    "PART NUMBER": "em97d90v53",
    "source": "external",
    "flocBarrierElementPrimary": "ingyvqwnaof0",
    "CALIBRATED RANGE MAX_UOM": "PoC",
    "SERIAL NUMBER": "d67f8ebd-de9e-4f28-8226-228f7b28b3a4",
    "SIGNAL TYPE": "Modbus",
    "HAZARDOUS AREA CERT NUMBER": "ykpe4gu75qwi",
    "createdTime": "2023-08-16T12:16:54.788Z",
    "SUPPLY CODE": "NA",
    "state": "1",
    "id": 8419511,
    "flocFunctionalLocation": "kzl8xtdlh7",
    "WEIGHT (DRY)": 2.22,
    "MODEL NUMBER": "zoxuzn3",
    "I/O TYPE": "AO",
    "System": "77: Ventisjon Sys",
    "Discipline": "E: Electrical",
    "HAZARDOUS AREA TEMP RATING (AS REQUIRED)": "T4",
    "PARENT TAG": "p2i2vq72ox",
    "flocSystemId": 83,
    "SET POINT HIGH HIGH_UOM": "iY",
    "flocLocation": "xw8v",
    "SAP CATALOG PROFILE": "8xaa6jby",
    "FIRE AREA": "19nz",
    "CALIBRATED RANGE MAX": 212.64,
    "LAST MAINTENANCE DATE": "2023-08-16T21:14:08.751Z",
    "CALIBRATION DATE": "2023-08-21T06:14:25.070Z",
    "LAST INSPECTION DATE": "2023-08-21T08:22:28.338Z"
  },
  {
    "SET POINT HIGH HIGH": 165.23,
    "sapParentAvevaExternalId": "04b1c259-8dda-4a9a-9b25-0c2c2c874092",
    "Issued By": "Dilanka",
    "SAP OBJECT TYPE": "IP-IOFT",
    "HAZARDOUS ATEX MARKING": "II 4 F",
    "PART NUMBER": "n0vauzb1zz",
    "source": "sap",
    "flocBarrierElementPrimary": "mqwoxne7u1fo",
    "CALIBRATED RANGE MAX_UOM": "PoC",
    "SERIAL NUMBER": "7bd42b70-14b0-4795-a6cc-38b82622f421",
    "SIGNAL TYPE": "Modbus",
    "HAZARDOUS AREA CERT NUMBER": "lr74hggmoab8",
    "createdTime": "2023-08-19T20:41:50.523Z",
    "SUPPLY CODE": "EU",
    "state": "0",
    "id": 8335227,
    "flocFunctionalLocation": "v6vy2u3v7a",
    "WEIGHT (DRY)": 2.91,
    "MODEL NUMBER": "gwqvijr",
    "I/O TYPE": "DO",
    "System": "77: Ventisjon Sys",
    "Discipline": "G: Gaseous sabstances",
    "HAZARDOUS AREA TEMP RATING (AS REQUIRED)": "T6",
    "PARENT TAG": "0no26hmxiv",
    "flocSystemId": 92,
    "SET POINT HIGH HIGH_UOM": "oF",
    "flocLocation": "ti8d",
    "SAP CATALOG PROFILE": "ir2mo3yx",
    "FIRE AREA": "ffkm",
    "CALIBRATED RANGE MAX": 181.16,
    "LAST MAINTENANCE DATE": "2023-08-17T01:29:36.057Z",
    "CALIBRATION DATE": "2023-08-21T07:43:53.776Z",
    "LAST INSPECTION DATE": "2023-08-20T12:10:47.414Z"
  },
  {
    "SET POINT HIGH HIGH": 152.48,
    "sapParentAvevaExternalId": "9a6b099d-e1b9-44fa-86dc-b1636f53c8d0",
    "Issued By": "Haakon",
    "SAP OBJECT TYPE": "IP-IOFT",
    "HAZARDOUS ATEX MARKING": "II 12 oiu",
    "PART NUMBER": "lh05ppd3az",
    "source": "aveva",
    "flocBarrierElementPrimary": "1gy10ptnoa3l",
    "CALIBRATED RANGE MAX_UOM": "PoC",
    "SERIAL NUMBER": "679f191d-3957-44b7-a1fa-df245e2652e2",
    "SIGNAL TYPE": "0-10V",
    "HAZARDOUS AREA CERT NUMBER": "rhop3dje9qnu",
    "createdTime": "2023-08-22T17:26:25.023Z",
    "SUPPLY CODE": "EU",
    "state": "0",
    "id": 8686783,
    "flocFunctionalLocation": "gzaf58n77x",
    "WEIGHT (DRY)": 2.42,
    "MODEL NUMBER": "01j8wtw",
    "I/O TYPE": "DI",
    "System": "32: Material uploading Sys",
    "Discipline": "G: Gaseous sabstances",
    "HAZARDOUS AREA TEMP RATING (AS REQUIRED)": "T4",
    "PARENT TAG": "a3i0b178xw",
    "flocSystemId": 21,
    "SET POINT HIGH HIGH_UOM": "oC",
    "flocLocation": "g6qu",
    "SAP CATALOG PROFILE": "8ryfv3ol",
    "FIRE AREA": "7mrj",
    "CALIBRATED RANGE MAX": 189.23,
    "LAST MAINTENANCE DATE": "2023-08-21T10:45:18.942Z",
    "CALIBRATION DATE": "2023-08-25T09:17:05.821Z",
    "LAST INSPECTION DATE": "2023-08-16T16:39:19.264Z"
  },
  {
    "SET POINT HIGH HIGH": 159.44,
    "sapParentAvevaExternalId": "abfc7a0e-b80b-462c-9b6a-59adfd27801b",
    "Issued By": "Vaibhav",
    "SAP OBJECT TYPE": "IP-IOFT",
    "HAZARDOUS ATEX MARKING": "II 12 oiu",
    "PART NUMBER": "0z81ye404w",
    "source": "sap",
    "flocBarrierElementPrimary": "2zeezokkgi3d",
    "CALIBRATED RANGE MAX_UOM": "oC",
    "SERIAL NUMBER": "4f66e65f-5bb5-41ca-a679-38de6f8a3d35",
    "SIGNAL TYPE": "Modbus",
    "HAZARDOUS AREA CERT NUMBER": "quwudrwpzz5f",
    "createdTime": "2023-08-21T10:18:00.930Z",
    "SUPPLY CODE": "ASIA",
    "state": "1",
    "id": 8652740,
    "flocFunctionalLocation": "zld2rqa05j",
    "WEIGHT (DRY)": 2.34,
    "MODEL NUMBER": "yxh1bk5",
    "I/O TYPE": "DI",
    "System": "32: Material uploading Sys",
    "Discipline": "A: Assemply and Installation",
    "HAZARDOUS AREA TEMP RATING (AS REQUIRED)": "T5",
    "PARENT TAG": "vhx5pikj6w",
    "flocSystemId": 14,
    "SET POINT HIGH HIGH_UOM": "oC",
    "flocLocation": "ui36",
    "SAP CATALOG PROFILE": "4muh3i8e",
    "FIRE AREA": "mlzu",
    "CALIBRATED RANGE MAX": 193.58,
    "LAST MAINTENANCE DATE": "2023-08-17T00:27:36.076Z",
    "CALIBRATION DATE": "2023-08-19T09:48:15.711Z",
    "LAST INSPECTION DATE": "2023-08-23T21:35:26.789Z"
  },
  {
    "SET POINT HIGH HIGH": 155.26,
    "sapParentAvevaExternalId": "c7bd5491-f97b-46b5-b3d5-50220cb9e1d1",
    "Issued By": "Ole",
    "SAP OBJECT TYPE": "IP-IOFT",
    "HAZARDOUS ATEX MARKING": "II 1 G",
    "PART NUMBER": "62txb840qi",
    "source": "ION",
    "flocBarrierElementPrimary": "4pqpn0u8w4d7",
    "CALIBRATED RANGE MAX_UOM": "PoC",
    "SERIAL NUMBER": "87e8aa1b-889d-4256-ba8f-8dbe72294a51",
    "SIGNAL TYPE": "0-10V",
    "HAZARDOUS AREA CERT NUMBER": "d71kdwv9rnch",
    "createdTime": "2023-08-24T11:47:11.391Z",
    "SUPPLY CODE": "EU",
    "state": "1",
    "id": 8976994,
    "flocFunctionalLocation": "tva35modgm",
    "WEIGHT (DRY)": 2.2,
    "MODEL NUMBER": "06k7irb",
    "I/O TYPE": "DI",
    "System": "22: GAS PROCESSING",
    "Discipline": "F: Facility handling",
    "HAZARDOUS AREA TEMP RATING (AS REQUIRED)": "T4",
    "PARENT TAG": "2hs91hxvv7",
    "flocSystemId": 21,
    "SET POINT HIGH HIGH_UOM": "oL",
    "flocLocation": "04cy",
    "SAP CATALOG PROFILE": "mzhntnlo",
    "FIRE AREA": "mwqo",
    "CALIBRATED RANGE MAX": 215.05,
    "LAST MAINTENANCE DATE": "2023-08-22T07:35:30.505Z",
    "CALIBRATION DATE": "2023-08-19T10:26:56.799Z",
    "LAST INSPECTION DATE": "2023-08-24T21:45:44.009Z"
  },
  {
    "SET POINT HIGH HIGH": 151.37,
    "sapParentAvevaExternalId": "0cdc2fc6-acbb-4766-ab25-f05c8885a5f1",
    "Issued By": "Ole",
    "SAP OBJECT TYPE": "IP-IOFT",
    "HAZARDOUS ATEX MARKING": "II 6 HJ",
    "PART NUMBER": "s2qq6r8xgk",
    "source": "external",
    "flocBarrierElementPrimary": "bx6kci9e1b99",
    "CALIBRATED RANGE MAX_UOM": "oF",
    "SERIAL NUMBER": "e45c826f-20e1-4008-9c95-0d38e7ae03dc",
    "SIGNAL TYPE": "0-10V",
    "HAZARDOUS AREA CERT NUMBER": "7rpw4epw7x7o",
    "createdTime": "2023-08-16T02:31:43.739Z",
    "SUPPLY CODE": "NA",
    "state": "0",
    "id": 8253063,
    "flocFunctionalLocation": "37brpnfdi4",
    "WEIGHT (DRY)": 2.66,
    "MODEL NUMBER": "zim576u",
    "I/O TYPE": "DI",
    "System": "11: Crane and fabrication",
    "Discipline": "C: Crane and material",
    "HAZARDOUS AREA TEMP RATING (AS REQUIRED)": "T4",
    "PARENT TAG": "xsdqmtk441",
    "flocSystemId": 55,
    "SET POINT HIGH HIGH_UOM": "oF",
    "flocLocation": "5lpz",
    "SAP CATALOG PROFILE": "w1jt30g6",
    "FIRE AREA": "dgee",
    "CALIBRATED RANGE MAX": 219.11,
    "LAST MAINTENANCE DATE": "2023-08-20T08:25:59.762Z",
    "CALIBRATION DATE": "2023-08-21T23:22:55.093Z",
    "LAST INSPECTION DATE": "2023-08-19T06:16:06.253Z"
  },
  {
    "SET POINT HIGH HIGH": 160.23,
    "sapParentAvevaExternalId": "fd4566fa-497e-4e22-8b54-d9aa9e5ea801",
    "Issued By": "Haakon",
    "SAP OBJECT TYPE": "IP-IOFT",
    "HAZARDOUS ATEX MARKING": "II 2 G",
    "PART NUMBER": "0zhxek38z2",
    "source": "sap",
    "flocBarrierElementPrimary": "32ksqdojnh1a",
    "CALIBRATED RANGE MAX_UOM": "PoC",
    "SERIAL NUMBER": "0ee1cb35-f898-4802-bc60-447de3484f2f",
    "SIGNAL TYPE": "4-20mA",
    "HAZARDOUS AREA CERT NUMBER": "miie05fedzko",
    "createdTime": "2023-08-17T18:49:02.783Z",
    "SUPPLY CODE": "NA",
    "state": "0",
    "id": 8435225,
    "flocFunctionalLocation": "u4zd4g94io",
    "WEIGHT (DRY)": 2.96,
    "MODEL NUMBER": "6ve7htp",
    "I/O TYPE": "AO",
    "System": "21: CRUDE HANDLING AND METERING",
    "Discipline": "J: Jagan and magan",
    "HAZARDOUS AREA TEMP RATING (AS REQUIRED)": "T5",
    "PARENT TAG": "2kcpio4zq5",
    "flocSystemId": 1,
    "SET POINT HIGH HIGH_UOM": "oL",
    "flocLocation": "elum",
    "SAP CATALOG PROFILE": "zww2ttae",
    "FIRE AREA": "4uy0",
    "CALIBRATED RANGE MAX": 193.67,
    "LAST MAINTENANCE DATE": "2023-08-18T01:28:46.171Z",
    "CALIBRATION DATE": "2023-08-22T00:47:38.865Z",
    "LAST INSPECTION DATE": "2023-08-25T15:02:51.895Z"
  },
  {
    "SET POINT HIGH HIGH": 157.34,
    "sapParentAvevaExternalId": "8f0f9414-12f0-4e2a-842f-25e78c5d4fb3",
    "Issued By": "Lisa",
    "SAP OBJECT TYPE": "IP-TIUT",
    "HAZARDOUS ATEX MARKING": "II 12 oiu",
    "PART NUMBER": "o1g2wkma6o",
    "source": "ION",
    "flocBarrierElementPrimary": "m5kqh9mk8p6k",
    "CALIBRATED RANGE MAX_UOM": "PoC",
    "SERIAL NUMBER": "b694cb4e-742e-41ce-90f8-b9d60e88e2ea",
    "SIGNAL TYPE": "4-20mA",
    "HAZARDOUS AREA CERT NUMBER": "02ttyx30uvds",
    "createdTime": "2023-08-15T22:35:06.613Z",
    "SUPPLY CODE": "ASIA",
    "state": "1",
    "id": 8485926,
    "flocFunctionalLocation": "4waig9m62c",
    "WEIGHT (DRY)": 2.01,
    "MODEL NUMBER": "bbpawtj",
    "I/O TYPE": "AI",
    "System": "23: UTILITIES",
    "Discipline": "A: Assemply and Installation",
    "HAZARDOUS AREA TEMP RATING (AS REQUIRED)": "T5",
    "PARENT TAG": "plgj5syz0h",
    "flocSystemId": 2,
    "SET POINT HIGH HIGH_UOM": "oL",
    "flocLocation": "n0ay",
    "SAP CATALOG PROFILE": "aax2di5v",
    "FIRE AREA": "li7f",
    "CALIBRATED RANGE MAX": 208.15,
    "LAST MAINTENANCE DATE": "2023-08-25T20:52:26.373Z",
    "CALIBRATION DATE": "2023-08-16T20:55:25.313Z",
    "LAST INSPECTION DATE": "2023-08-22T20:46:14.364Z"
  },
  {
    "SET POINT HIGH HIGH": 161.43,
    "sapParentAvevaExternalId": "1c81d19a-b2ae-48fb-a8f6-0e4ed793ff7c",
    "Issued By": "Lisa",
    "SAP OBJECT TYPE": "IP-KJPT",
    "HAZARDOUS ATEX MARKING": "II 2 G",
    "PART NUMBER": "yg2oshxp7q",
    "source": "sap",
    "flocBarrierElementPrimary": "abmdirlnq305",
    "CALIBRATED RANGE MAX_UOM": "oF",
    "SERIAL NUMBER": "36341eb2-7973-4af1-bd65-ae3a7628a963",
    "SIGNAL TYPE": "Modbus",
    "HAZARDOUS AREA CERT NUMBER": "s1x9swmzro76",
    "createdTime": "2023-08-18T04:10:11.251Z",
    "SUPPLY CODE": "NA",
    "state": "0",
    "id": 8899615,
    "flocFunctionalLocation": "tcdnmcqnk1",
    "WEIGHT (DRY)": 2.36,
    "MODEL NUMBER": "1m05h2q",
    "I/O TYPE": "AI",
    "System": "11: Crane and fabrication",
    "Discipline": "G: Gaseous sabstances",
    "HAZARDOUS AREA TEMP RATING (AS REQUIRED)": "T6",
    "PARENT TAG": "r22hvhv7w6",
    "flocSystemId": 61,
    "SET POINT HIGH HIGH_UOM": "oL",
    "flocLocation": "n771",
    "SAP CATALOG PROFILE": "k67mcy7u",
    "FIRE AREA": "033f",
    "CALIBRATED RANGE MAX": 186.61,
    "LAST MAINTENANCE DATE": "2023-08-24T18:56:09.706Z",
    "CALIBRATION DATE": "2023-08-23T04:02:20.717Z",
    "LAST INSPECTION DATE": "2023-08-20T20:29:22.480Z"
  },
  {
    "SET POINT HIGH HIGH": 162.79,
    "sapParentAvevaExternalId": "3e202e8a-603e-45d5-9fc8-fd78259f3469",
    "Issued By": "Dilanka",
    "SAP OBJECT TYPE": "IP-KJPT",
    "HAZARDOUS ATEX MARKING": "II 3 G",
    "PART NUMBER": "3s60r9l6p9",
    "source": "external",
    "flocBarrierElementPrimary": "98be61g2uskt",
    "CALIBRATED RANGE MAX_UOM": "PoC",
    "SERIAL NUMBER": "f294465d-c505-4961-a0db-f19e8a183e00",
    "SIGNAL TYPE": "0-10V",
    "HAZARDOUS AREA CERT NUMBER": "bht4t2rszdev",
    "createdTime": "2023-08-19T15:51:16.606Z",
    "SUPPLY CODE": "EU",
    "state": "0",
    "id": 8087148,
    "flocFunctionalLocation": "7h3rvlneja",
    "WEIGHT (DRY)": 2.24,
    "MODEL NUMBER": "i1mo2ht",
    "I/O TYPE": "DO",
    "System": "32: Material uploading Sys",
    "Discipline": "I: Industrial equipments",
    "HAZARDOUS AREA TEMP RATING (AS REQUIRED)": "T6",
    "PARENT TAG": "sfynwrxf4a",
    "flocSystemId": 19,
    "SET POINT HIGH HIGH_UOM": "oC",
    "flocLocation": "6rb7",
    "SAP CATALOG PROFILE": "cuz8lvxn",
    "FIRE AREA": "jld1",
    "CALIBRATED RANGE MAX": 197.24,
    "LAST MAINTENANCE DATE": "2023-08-19T07:49:06.176Z",
    "CALIBRATION DATE": "2023-08-18T01:41:24.536Z",
    "LAST INSPECTION DATE": "2023-08-24T09:19:12.086Z"
  },
  {
    "SET POINT HIGH HIGH": 159.54,
    "sapParentAvevaExternalId": "6a2aa512-8b5e-49c6-966c-fc8f2d9d01c4",
    "Issued By": "Michael",
    "SAP OBJECT TYPE": "IP-TIUT",
    "HAZARDOUS ATEX MARKING": "II 9 GIJO",
    "PART NUMBER": "ra6e183s94",
    "source": "aveva",
    "flocBarrierElementPrimary": "aghhqwik45an",
    "CALIBRATED RANGE MAX_UOM": "oF",
    "SERIAL NUMBER": "b0d94f00-d9bc-4aea-904b-bc79eaf54426",
    "SIGNAL TYPE": "Modbus",
    "HAZARDOUS AREA CERT NUMBER": "wl1k37aglade",
    "createdTime": "2023-08-19T01:40:08.773Z",
    "SUPPLY CODE": "ASIA",
    "state": "1",
    "id": 8017207,
    "flocFunctionalLocation": "aauavb5kmg",
    "WEIGHT (DRY)": 2.28,
    "MODEL NUMBER": "dvs48f6",
    "I/O TYPE": "DI",
    "System": "31: Sub mechanical Sys",
    "Discipline": "A: Assemply and Installation",
    "HAZARDOUS AREA TEMP RATING (AS REQUIRED)": "T5",
    "PARENT TAG": "46gilqw84n",
    "flocSystemId": 32,
    "SET POINT HIGH HIGH_UOM": "oC",
    "flocLocation": "uj9h",
    "SAP CATALOG PROFILE": "q9rnezgq",
    "FIRE AREA": "dvd9",
    "CALIBRATED RANGE MAX": 216.77,
    "LAST MAINTENANCE DATE": "2023-08-23T04:33:29.663Z",
    "CALIBRATION DATE": "2023-08-19T08:08:09.607Z",
    "LAST INSPECTION DATE": "2023-08-21T09:57:07.421Z"
  },
  {
    "SET POINT HIGH HIGH": 161.52,
    "sapParentAvevaExternalId": "4c483649-64cd-4476-8852-82b568428ef9",
    "Issued By": "Lisa",
    "SAP OBJECT TYPE": "IP-IOFT",
    "HAZARDOUS ATEX MARKING": "II 12 oiu",
    "PART NUMBER": "jgo6qpk1t2",
    "source": "sap",
    "flocBarrierElementPrimary": "unllvixf9uqm",
    "CALIBRATED RANGE MAX_UOM": "oF",
    "SERIAL NUMBER": "3175ec77-fc44-4f37-ac53-ab7ffd8321a7",
    "SIGNAL TYPE": "Modbus",
    "HAZARDOUS AREA CERT NUMBER": "7czrng8n4bia",
    "createdTime": "2023-08-18T17:42:00.683Z",
    "SUPPLY CODE": "EU",
    "state": "0",
    "id": 8454284,
    "flocFunctionalLocation": "9vc0fozdrh",
    "WEIGHT (DRY)": 2.2,
    "MODEL NUMBER": "naku760",
    "I/O TYPE": "DO",
    "System": "21: CRUDE HANDLING AND METERING",
    "Discipline": "E: Electrical",
    "HAZARDOUS AREA TEMP RATING (AS REQUIRED)": "T5",
    "PARENT TAG": "mzgle8qpre",
    "flocSystemId": 41,
    "SET POINT HIGH HIGH_UOM": "iY",
    "flocLocation": "sl7l",
    "SAP CATALOG PROFILE": "jjg6yeg9",
    "FIRE AREA": "icui",
    "CALIBRATED RANGE MAX": 190.34,
    "LAST MAINTENANCE DATE": "2023-08-22T23:48:57.581Z",
    "CALIBRATION DATE": "2023-08-25T17:27:09.093Z",
    "LAST INSPECTION DATE": "2023-08-16T12:10:23.303Z"
  },
  {
    "SET POINT HIGH HIGH": 165.17,
    "sapParentAvevaExternalId": "ef8b9055-1d84-4a03-9647-8902d3525866",
    "Issued By": "Samit",
    "SAP OBJECT TYPE": "IP-TIUT",
    "HAZARDOUS ATEX MARKING": "II 9 GIJO",
    "PART NUMBER": "nyivn5ulkt",
    "source": "sap",
    "flocBarrierElementPrimary": "pt3g4b426c6q",
    "CALIBRATED RANGE MAX_UOM": "PoC",
    "SERIAL NUMBER": "bfab055d-7ef0-4dcb-a324-c4f74b5e8b7f",
    "SIGNAL TYPE": "4-20mA",
    "HAZARDOUS AREA CERT NUMBER": "pfklbweoq7ru",
    "createdTime": "2023-08-24T09:57:08.214Z",
    "SUPPLY CODE": "ASIA",
    "state": "1",
    "id": 8453059,
    "flocFunctionalLocation": "qfd9n7hh4a",
    "WEIGHT (DRY)": 2.7,
    "MODEL NUMBER": "697liif",
    "I/O TYPE": "AI",
    "System": "77: Ventisjon Sys",
    "Discipline": "A: Assemply and Installation",
    "HAZARDOUS AREA TEMP RATING (AS REQUIRED)": "T4",
    "PARENT TAG": "qk1qizlpfr",
    "flocSystemId": 62,
    "SET POINT HIGH HIGH_UOM": "oF",
    "flocLocation": "2jfp",
    "SAP CATALOG PROFILE": "y2s9uzi6",
    "FIRE AREA": "6i4s",
    "CALIBRATED RANGE MAX": 202.47,
    "LAST MAINTENANCE DATE": "2023-08-25T18:07:21.047Z",
    "CALIBRATION DATE": "2023-08-23T20:19:21.006Z",
    "LAST INSPECTION DATE": "2023-08-17T09:24:36.790Z"
  },
  {
    "SET POINT HIGH HIGH": 150.09,
    "sapParentAvevaExternalId": "a4c5c1bb-472a-4873-8138-82913412c042",
    "Issued By": "Lisa",
    "SAP OBJECT TYPE": "IP-KJPT",
    "HAZARDOUS ATEX MARKING": "II 1 G",
    "PART NUMBER": "q7tzu9z9w9",
    "source": "external",
    "flocBarrierElementPrimary": "fzslmir2r9l2",
    "CALIBRATED RANGE MAX_UOM": "oF",
    "SERIAL NUMBER": "968de261-a28d-49a0-a30d-5880edd32460",
    "SIGNAL TYPE": "4-20mA",
    "HAZARDOUS AREA CERT NUMBER": "fowhmzij8gse",
    "createdTime": "2023-08-20T23:16:11.736Z",
    "SUPPLY CODE": "ASIA",
    "state": "1",
    "id": 8829628,
    "flocFunctionalLocation": "j41ngyryjc",
    "WEIGHT (DRY)": 2.5,
    "MODEL NUMBER": "pe2p6e1",
    "I/O TYPE": "AO",
    "System": "11: Crane and fabrication",
    "Discipline": "E: Electrical",
    "HAZARDOUS AREA TEMP RATING (AS REQUIRED)": "T4",
    "PARENT TAG": "m9z5yqo64k",
    "flocSystemId": 59,
    "SET POINT HIGH HIGH_UOM": "oF",
    "flocLocation": "1rkn",
    "SAP CATALOG PROFILE": "br5gprfp",
    "FIRE AREA": "n7h0",
    "CALIBRATED RANGE MAX": 210.25,
    "LAST MAINTENANCE DATE": "2023-08-16T09:47:38.028Z",
    "CALIBRATION DATE": "2023-08-23T15:55:58.528Z",
    "LAST INSPECTION DATE": "2023-08-16T10:13:19.753Z"
  },
  {
    "SET POINT HIGH HIGH": 163.35,
    "sapParentAvevaExternalId": "d1552145-9839-4cec-acfd-d68120b7e199",
    "Issued By": "Ole",
    "SAP OBJECT TYPE": "IP-TIUT",
    "HAZARDOUS ATEX MARKING": "II 4 F",
    "PART NUMBER": "7fke4dj76w",
    "source": "sap",
    "flocBarrierElementPrimary": "hqruywzej6pc",
    "CALIBRATED RANGE MAX_UOM": "oF",
    "SERIAL NUMBER": "08f42d3e-64a4-48c3-878a-8680e00b5923",
    "SIGNAL TYPE": "4-20mA",
    "HAZARDOUS AREA CERT NUMBER": "z11tsr72r0y8",
    "createdTime": "2023-08-25T21:16:17.489Z",
    "SUPPLY CODE": "EU",
    "state": "1",
    "id": 8155297,
    "flocFunctionalLocation": "q9bzue996n",
    "WEIGHT (DRY)": 2.58,
    "MODEL NUMBER": "tc4fp6u",
    "I/O TYPE": "DI",
    "System": "21: CRUDE HANDLING AND METERING",
    "Discipline": "B: Biomarine and sanity",
    "HAZARDOUS AREA TEMP RATING (AS REQUIRED)": "T6",
    "PARENT TAG": "ot12aicl9n",
    "flocSystemId": 85,
    "SET POINT HIGH HIGH_UOM": "oF",
    "flocLocation": "alzn",
    "SAP CATALOG PROFILE": "x5bli69p",
    "FIRE AREA": "ojuv",
    "CALIBRATED RANGE MAX": 187.24,
    "LAST MAINTENANCE DATE": "2023-08-21T11:54:02.036Z",
    "CALIBRATION DATE": "2023-08-25T09:06:16.340Z",
    "LAST INSPECTION DATE": "2023-08-22T03:34:23.541Z"
  },
  {
    "SET POINT HIGH HIGH": 168.38,
    "sapParentAvevaExternalId": "a2ca2e23-8645-4980-9121-d6a7a7869dde",
    "Issued By": "Vaibhav",
    "SAP OBJECT TYPE": "IP-TIUT",
    "HAZARDOUS ATEX MARKING": "II 12 oiu",
    "PART NUMBER": "ol2g334wv2",
    "source": "aveva",
    "flocBarrierElementPrimary": "69kdvi01li0q",
    "CALIBRATED RANGE MAX_UOM": "PoC",
    "SERIAL NUMBER": "5748901e-8dcf-48fe-a0bf-54cbc515c628",
    "SIGNAL TYPE": "4-20mA",
    "HAZARDOUS AREA CERT NUMBER": "ggc4yw0efofc",
    "createdTime": "2023-08-25T14:34:38.036Z",
    "SUPPLY CODE": "ASIA",
    "state": "0",
    "id": 8701071,
    "flocFunctionalLocation": "4af0cckscr",
    "WEIGHT (DRY)": 2.4,
    "MODEL NUMBER": "6aee7dv",
    "I/O TYPE": "DO",
    "System": "11: Crane and fabrication",
    "Discipline": "D: Gas and toxic substance",
    "HAZARDOUS AREA TEMP RATING (AS REQUIRED)": "T4",
    "PARENT TAG": "3hzmdgreyy",
    "flocSystemId": 98,
    "SET POINT HIGH HIGH_UOM": "oF",
    "flocLocation": "l98u",
    "SAP CATALOG PROFILE": "wkyrb89y",
    "FIRE AREA": "4qb5",
    "CALIBRATED RANGE MAX": 204.89,
    "LAST MAINTENANCE DATE": "2023-08-16T00:39:52.064Z",
    "CALIBRATION DATE": "2023-08-19T01:21:18.629Z",
    "LAST INSPECTION DATE": "2023-08-24T00:50:58.730Z"
  },
  {
    "SET POINT HIGH HIGH": 168.13,
    "sapParentAvevaExternalId": "f17b0428-1572-4d09-9109-5329ed282396",
    "Issued By": "Michael",
    "SAP OBJECT TYPE": "IP-KJPT",
    "HAZARDOUS ATEX MARKING": "II 6 HJ",
    "PART NUMBER": "aiiqewbmks",
    "source": "aveva",
    "flocBarrierElementPrimary": "bvdmdgvti29o",
    "CALIBRATED RANGE MAX_UOM": "oF",
    "SERIAL NUMBER": "70c7e889-b134-4ea1-b501-79b139c8fab3",
    "SIGNAL TYPE": "Modbus",
    "HAZARDOUS AREA CERT NUMBER": "dqf17wglg0yn",
    "createdTime": "2023-08-24T00:15:11.947Z",
    "SUPPLY CODE": "EU",
    "state": "0",
    "id": 8680336,
    "flocFunctionalLocation": "be8sf8l41q",
    "WEIGHT (DRY)": 2.1,
    "MODEL NUMBER": "750l9pg",
    "I/O TYPE": "DI",
    "System": "21: CRUDE HANDLING AND METERING",
    "Discipline": "G: Gaseous sabstances",
    "HAZARDOUS AREA TEMP RATING (AS REQUIRED)": "T6",
    "PARENT TAG": "z4cawu9wrd",
    "flocSystemId": 8,
    "SET POINT HIGH HIGH_UOM": "oL",
    "flocLocation": "po7o",
    "SAP CATALOG PROFILE": "i6uh36gc",
    "FIRE AREA": "wo9h",
    "CALIBRATED RANGE MAX": 189.25,
    "LAST MAINTENANCE DATE": "2023-08-20T18:10:56.277Z",
    "CALIBRATION DATE": "2023-08-19T18:05:21.035Z",
    "LAST INSPECTION DATE": "2023-08-24T07:48:56.589Z"
  },
  {
    "SET POINT HIGH HIGH": 158.26,
    "sapParentAvevaExternalId": "19087b55-b21e-4254-bab2-759675dd6459",
    "Issued By": "Vaibhav",
    "SAP OBJECT TYPE": "IP-IOFT",
    "HAZARDOUS ATEX MARKING": "II 6 HJ",
    "PART NUMBER": "7hopsjnnul",
    "source": "external",
    "flocBarrierElementPrimary": "ah51y8e7004s",
    "CALIBRATED RANGE MAX_UOM": "oC",
    "SERIAL NUMBER": "d68ac7f4-ba67-42d7-974e-66d199a37e19",
    "SIGNAL TYPE": "0-10V",
    "HAZARDOUS AREA CERT NUMBER": "dxc1vjii62hv",
    "createdTime": "2023-08-23T08:45:13.398Z",
    "SUPPLY CODE": "ASIA",
    "state": "0",
    "id": 8963730,
    "flocFunctionalLocation": "q32k6ghrfb",
    "WEIGHT (DRY)": 2.07,
    "MODEL NUMBER": "l1jf6pz",
    "I/O TYPE": "AI",
    "System": "22: Sanitation Disposal system",
    "Discipline": "D: Gas and toxic substance",
    "HAZARDOUS AREA TEMP RATING (AS REQUIRED)": "T6",
    "PARENT TAG": "wknqhux0ts",
    "flocSystemId": 84,
    "SET POINT HIGH HIGH_UOM": "oC",
    "flocLocation": "qclv",
    "SAP CATALOG PROFILE": "v7kjvmmp",
    "FIRE AREA": "ovoz",
    "CALIBRATED RANGE MAX": 205.68,
    "LAST MAINTENANCE DATE": "2023-08-20T15:56:47.923Z",
    "CALIBRATION DATE": "2023-08-25T21:24:56.502Z",
    "LAST INSPECTION DATE": "2023-08-19T21:12:31.927Z"
  }
]